{"meta": {"count": 228, "db_response_time_ms": 47, "page": 1, "per_page": 200, "groups_count": null, "cost_usd": 0.0001}
, "results": [
  {"id": "https://openalex.org/W977705565", "title": "Generalized Blockmodeling", "countries_distinct_count": 2, "cited_by_count": 472, "referenced_works_count": 0}
, {"id": "https://openalex.org/W2070882870", "title": "A partitioning approach to structural balance", "countries_distinct_count": 2, "cited_by_count": 306, "referenced_works_count": 23}
, {"id": "https://openalex.org/W2106631101", "title": "Linear Models with Spatially Distributed Data", "countries_distinct_count": 1, "cited_by_count": 282, "referenced_works_count": 20}
, {"id": "https://openalex.org/W2164181247", "title": "Some dynamics of social balance processes: bringing Heider back into balance theory", "countries_distinct_count": 1, "cited_by_count": 271, "referenced_works_count": 32}
, {"id": "https://openalex.org/W2102664282", "title": "Partitioning signed social networks", "countries_distinct_count": 2, "cited_by_count": 220, "referenced_works_count": 23}
, {"id": "https://openalex.org/W1981385379", "title": "Generalized blockmodeling of two-mode network data", "countries_distinct_count": 2, "cited_by_count": 201, "referenced_works_count": 32}
, {"id": "https://openalex.org/W1975997085", "title": "Social context, spatial structure and social network structure", "countries_distinct_count": 2, "cited_by_count": 179, "referenced_works_count": 39}
, {"id": "https://openalex.org/W2606121346", "title": "With whom do researchers collaborate and why?", "countries_distinct_count": 2, "cited_by_count": 124, "referenced_works_count": 99}
, {"id": "https://openalex.org/W2031751296", "title": "A brief history of balance through time", "countries_distinct_count": 1, "cited_by_count": 120, "referenced_works_count": 46}
, {"id": "https://openalex.org/W2605255209", "title": "Structural Balance and Signed International Relations", "countries_distinct_count": 2, "cited_by_count": 118, "referenced_works_count": 63}
, {"id": "https://openalex.org/W2289547538", "title": "Measuring Patterns of Acquaintanceship [and Comments and Reply]", "countries_distinct_count": 0, "cited_by_count": 108, "referenced_works_count": 6}
, {"id": "https://openalex.org/W2015739448", "title": "Scientific collaboration dynamics in a national scientific system", "countries_distinct_count": 2, "cited_by_count": 99, "referenced_works_count": 50}
, {"id": "https://openalex.org/W2097444198", "title": "On the dynamics of national scientific systems", "countries_distinct_count": 2, "cited_by_count": 88, "referenced_works_count": 38}
, {"id": "https://openalex.org/W2561083738", "title": "OUP accepted manuscript", "countries_distinct_count": 3, "cited_by_count": 60, "referenced_works_count": 56}
, {"id": "https://openalex.org/W2010757184", "title": "Estimating Linear Models with Spatially Distributed Data", "countries_distinct_count": 0, "cited_by_count": 168, "referenced_works_count": 10}
, {"id": "https://openalex.org/W2061405566", "title": "The Problem of Solidarity: Theories and Models", "countries_distinct_count": 0, "cited_by_count": 155, "referenced_works_count": 0}
, {"id": "https://openalex.org/W2023723604", "title": "Direct and indirect methods for structural equivalence", "countries_distinct_count": 2, "cited_by_count": 128, "referenced_works_count": 24}
, {"id": "https://openalex.org/W2020906890", "title": "Fixed list versus snowball selection of social networks", "countries_distinct_count": 1, "cited_by_count": 122, "referenced_works_count": 16}
, {"id": "https://openalex.org/W2034368872", "title": "Structural equivalence in a journal network", "countries_distinct_count": 1, "cited_by_count": 104, "referenced_works_count": 22}
, {"id": "https://openalex.org/W2001947224", "title": "An optimizational approach to regular equivalence", "countries_distinct_count": 2, "cited_by_count": 103, "referenced_works_count": 11}
, {"id": "https://openalex.org/W2056270883", "title": "Defining and locating cores and boundaries of social networks", "countries_distinct_count": 1, "cited_by_count": 103, "referenced_works_count": 33}
, {"id": "https://openalex.org/W2081494945", "title": "Causality in Social Network Analysis", "countries_distinct_count": 1, "cited_by_count": 94, "referenced_works_count": 57}
, {"id": "https://openalex.org/W2135942694", "title": "Collaboration structures in Slovenian scientific communities", "countries_distinct_count": 2, "cited_by_count": 93, "referenced_works_count": 39}
, {"id": "https://openalex.org/W2133028771", "title": "Structural equivalence in a psychology journal network", "countries_distinct_count": 1, "cited_by_count": 91, "referenced_works_count": 23}
, {"id": "https://openalex.org/W2166951268", "title": "Analyzing the Structure of the Centrality-Productivity Literature Created Between 1948 and 1979", "countries_distinct_count": 1, "cited_by_count": 91, "referenced_works_count": 96}
, {"id": "https://openalex.org/W2033421843", "title": "Pre\u2010transitive balance mechanisms for signed networks*", "countries_distinct_count": 2, "cited_by_count": 88, "referenced_works_count": 31}
, {"id": "https://openalex.org/W1981659521", "title": "Tripartite structural analysis: Generalizing the Breiger-Wilson formalism", "countries_distinct_count": 1, "cited_by_count": 84, "referenced_works_count": 25}
, {"id": "https://openalex.org/W1990126606", "title": "Network Autocorrelation Models", "countries_distinct_count": 1, "cited_by_count": 82, "referenced_works_count": 8}
, {"id": "https://openalex.org/W143494085", "title": "Dynamic Scientific Co-Authorship Networks", "countries_distinct_count": 2, "cited_by_count": 73, "referenced_works_count": 159}
, {"id": "https://openalex.org/W2036653794", "title": "On the connectivity of social networks\u2020", "countries_distinct_count": 1, "cited_by_count": 73, "referenced_works_count": 8}
, {"id": "https://openalex.org/W2090623833", "title": "Partitioning large signed two-mode networks: Problems and prospects", "countries_distinct_count": 2, "cited_by_count": 69, "referenced_works_count": 63}
, {"id": "https://openalex.org/W2049626205", "title": "Computational methods for social network analysis", "countries_distinct_count": 1, "cited_by_count": 68, "referenced_works_count": 9}
, {"id": "https://openalex.org/W2100597279", "title": "Social network engineering and race in a police academy: A longitudinal analysis", "countries_distinct_count": 2, "cited_by_count": 67, "referenced_works_count": 34}
, {"id": "https://openalex.org/W2011924621", "title": "On the evolution of group and network structure", "countries_distinct_count": 1, "cited_by_count": 55, "referenced_works_count": 23}
, {"id": "https://openalex.org/W2087189283", "title": "Introduction to the special issue on network dynamics", "countries_distinct_count": 4, "cited_by_count": 55, "referenced_works_count": 23}
, {"id": "https://openalex.org/W2094907462", "title": "Equivalence in a social network", "countries_distinct_count": 1, "cited_by_count": 50, "referenced_works_count": 34}
, {"id": "https://openalex.org/W2115454210", "title": "Actor network utilities and network evolution", "countries_distinct_count": 1, "cited_by_count": 49, "referenced_works_count": 22}
, {"id": "https://openalex.org/W2155999268", "title": "Non-response in social networks: The impact of different non-response treatments on the stability of blockmodels", "countries_distinct_count": 2, "cited_by_count": 49, "referenced_works_count": 49}
, {"id": "https://openalex.org/W2315898249", "title": "A Structural Control Model of Organizational Change", "countries_distinct_count": 0, "cited_by_count": 48, "referenced_works_count": 1}
, {"id": "https://openalex.org/W563958427", "title": "Understanding Large Temporal Networks and Spatial Networks: Exploration, Pattern Searching, Visualization and Network Evolution", "countries_distinct_count": 0, "cited_by_count": 44, "referenced_works_count": 0}
, {"id": "https://openalex.org/W206232026", "title": "Generalized Blockmodeling (Structural Analysis in the Social Sciences)", "countries_distinct_count": 0, "cited_by_count": 42, "referenced_works_count": 0}
, {"id": "https://openalex.org/W2332964253", "title": "From Here On Out, We\u2019re All Blue: Interaction Order, Social Infrastructure, and Race in Police Socialization", "countries_distinct_count": 2, "cited_by_count": 35, "referenced_works_count": 128}
, {"id": "https://openalex.org/W2142936616", "title": "Generalized blockmodeling with Pajek", "countries_distinct_count": 2, "cited_by_count": 34, "referenced_works_count": 15}
, {"id": "https://openalex.org/W2047529619", "title": "Partitioning Signed Two-Mode Networks", "countries_distinct_count": 2, "cited_by_count": 31, "referenced_works_count": 21}
, {"id": "https://openalex.org/W2607533199", "title": "Creating the thin blue line: Social network evolution within a police academy", "countries_distinct_count": 2, "cited_by_count": 31, "referenced_works_count": 54}
, {"id": "https://openalex.org/W2166513527", "title": "Multiobjective Blockmodeling for Social Network Analysis", "countries_distinct_count": 2, "cited_by_count": 24, "referenced_works_count": 69}
, {"id": "https://openalex.org/W108600343", "title": "Spatial Statistics: Past, Present, and Future", "countries_distinct_count": 0, "cited_by_count": 129, "referenced_works_count": 0}
, {"id": "https://openalex.org/W1995347297", "title": "Maximum Likelihood Methods for Linear Models", "countries_distinct_count": 1, "cited_by_count": 54, "referenced_works_count": 15}
, {"id": "https://openalex.org/W2023553157", "title": "Testing a structural model of perception: Conformity and deviance with respect to Journal norms in elite sociological methodology", "countries_distinct_count": 1, "cited_by_count": 48, "referenced_works_count": 60}
, {"id": "https://openalex.org/W2150505601", "title": "Event sequences as generators of social network evolution", "countries_distinct_count": 1, "cited_by_count": 47, "referenced_works_count": 46}
, {"id": "https://openalex.org/W2162146505", "title": "A multiple indicator approach to blockmodeling signed networks", "countries_distinct_count": 1, "cited_by_count": 35, "referenced_works_count": 53}
, {"id": "https://openalex.org/W1966812833", "title": "Two Algorithms for Relaxed Structural Balance Partitioning: Linking Theory, Models, and Data to Understand Social Network Phenomena", "countries_distinct_count": 2, "cited_by_count": 33, "referenced_works_count": 43}
, {"id": "https://openalex.org/W2118857153", "title": "Positional Analyses of Sociometric Data", "countries_distinct_count": 2, "cited_by_count": 30, "referenced_works_count": 22}
, {"id": "https://openalex.org/W2184535351", "title": "Positions and Roles", "countries_distinct_count": 0, "cited_by_count": 29, "referenced_works_count": 47}
, {"id": "https://openalex.org/W2206523813", "title": "Examining the effect of social influence on student performance through network autocorrelation models", "countries_distinct_count": 3, "cited_by_count": 28, "referenced_works_count": 47}
, {"id": "https://openalex.org/W2078104673", "title": "A measure of standing of journals in stratified networks", "countries_distinct_count": 1, "cited_by_count": 27, "referenced_works_count": 29}
, {"id": "https://openalex.org/W2103458262", "title": "Classifying scientific disciplines in <scp>S</scp>lovenia: A study of the evolution of collaboration structures", "countries_distinct_count": 2, "cited_by_count": 25, "referenced_works_count": 52}
, {"id": "https://openalex.org/W2118112947", "title": "Fitting Pre-specified Blockmodels", "countries_distinct_count": 2, "cited_by_count": 25, "referenced_works_count": 8}
, {"id": "https://openalex.org/W2147731720", "title": "Understanding a collaborative effort to reduce racial and ethnic disparities in health care: Contributions from social network analysis", "countries_distinct_count": 1, "cited_by_count": 22, "referenced_works_count": 19}
, {"id": "https://openalex.org/W2156402754", "title": "Contrasting Multiple Social Network Autocorrelations for Binary Outcomes, With Applications To Technology Adoption", "countries_distinct_count": 2, "cited_by_count": 21, "referenced_works_count": 33}
, {"id": "https://openalex.org/W2509618548", "title": "Actor non-response in valued social networks: The impact of different non-response treatments on the stability of blockmodels", "countries_distinct_count": 2, "cited_by_count": 20, "referenced_works_count": 60}
, {"id": "https://openalex.org/W2893740070", "title": "Partitioning signed networks using relocation heuristics, tabu search, and variable neighborhood search", "countries_distinct_count": 2, "cited_by_count": 18, "referenced_works_count": 78}
, {"id": "https://openalex.org/W2499300184", "title": "Network Data Sets", "countries_distinct_count": 2, "cited_by_count": 17, "referenced_works_count": 0}
, {"id": "https://openalex.org/W2147729976", "title": "A variable neighborhood search method for a two-mode blockmodeling problem in social network analysis", "countries_distinct_count": 2, "cited_by_count": 16, "referenced_works_count": 47}
, {"id": "https://openalex.org/W2240460603", "title": "Finding roles in sparse economic hierarchies: Going beyond regular equivalence", "countries_distinct_count": 3, "cited_by_count": 15, "referenced_works_count": 31}
, {"id": "https://openalex.org/W1986877555", "title": "A real-coded genetic algorithm for two-mode KL-means partitioning with application to homogeneity blockmodeling", "countries_distinct_count": 2, "cited_by_count": 12, "referenced_works_count": 49}
, {"id": "https://openalex.org/W2052607635", "title": "An Exact Algorithm for Blockmodeling of Two-Mode Network Data", "countries_distinct_count": 2, "cited_by_count": 11, "referenced_works_count": 55}
, {"id": "https://openalex.org/W4205784087", "title": "Testing two theories for generating signed networks using real data", "countries_distinct_count": 2, "cited_by_count": 11, "referenced_works_count": 35}
, {"id": "https://openalex.org/W3090988463", "title": "Hubs and Authorities in the Koch Brothers Network", "countries_distinct_count": 2, "cited_by_count": 10, "referenced_works_count": 25}
, {"id": "https://openalex.org/W4382068596", "title": "Police recruit narratives and publicly oriented vocabularies of motive", "countries_distinct_count": 2, "cited_by_count": 5, "referenced_works_count": 30}
, {"id": "https://openalex.org/W2067438539", "title": "Partitioning networks based on generalized concepts of equivalence", "countries_distinct_count": 2, "cited_by_count": 53, "referenced_works_count": 18}
, {"id": "https://openalex.org/W2126157859", "title": "Symmetric-Acyclic Decompositions of Networks", "countries_distinct_count": 2, "cited_by_count": 51, "referenced_works_count": 17}
, {"id": "https://openalex.org/W2509817277", "title": "A Note on the Detection of Cliques in Valued Graphs", "countries_distinct_count": 0, "cited_by_count": 48, "referenced_works_count": 4}
, {"id": "https://openalex.org/W1995489261", "title": "Measuring regular equivalence in symmetric structures", "countries_distinct_count": 1, "cited_by_count": 31, "referenced_works_count": 10}
, {"id": "https://openalex.org/W2010182968", "title": "Measuring the relative standing of disciplinary journals", "countries_distinct_count": 1, "cited_by_count": 30, "referenced_works_count": 33}
, {"id": "https://openalex.org/W2064903341", "title": "A revised measure of standing of journals in stratified networks", "countries_distinct_count": 1, "cited_by_count": 29, "referenced_works_count": 18}
, {"id": "https://openalex.org/W2139058500", "title": "Evolution of human signed networks", "countries_distinct_count": 1, "cited_by_count": 19, "referenced_works_count": 16}
, {"id": "https://openalex.org/W1037954096", "title": "Indirect Blockmodeling of 3-Way Networks", "countries_distinct_count": 2, "cited_by_count": 13, "referenced_works_count": 11}
, {"id": "https://openalex.org/W1482919069", "title": "Positional Analysis and Blockmodeling", "countries_distinct_count": 1, "cited_by_count": 13, "referenced_works_count": 21}
, {"id": "https://openalex.org/W2108047128", "title": "Introduction to the special issue on Network Dynamics (Part 2)", "countries_distinct_count": 3, "cited_by_count": 12, "referenced_works_count": 13}
, {"id": "https://openalex.org/W2766632047", "title": "Stability of centrality measures in valued networks regarding different actor non-response treatments and macro-network structures", "countries_distinct_count": 2, "cited_by_count": 10, "referenced_works_count": 45}
, {"id": "https://openalex.org/W2237311910", "title": "An Exact Algorithm for the Two-Mode KL-Means Partitioning Problem", "countries_distinct_count": 2, "cited_by_count": 9, "referenced_works_count": 56}
, {"id": "https://openalex.org/W2567966427", "title": "Identifying Fragments in Networks for Structural Balance and Tracking the Levels of Balance Over Time", "countries_distinct_count": 2, "cited_by_count": 7, "referenced_works_count": 14}
, {"id": "https://openalex.org/W2142029339", "title": "Biclustering methods for one-mode asymmetric matrices", "countries_distinct_count": 2, "cited_by_count": 6, "referenced_works_count": 72}
, {"id": "https://openalex.org/W4300851886", "title": "Networks in Social Psychology, Beginning with Kurt Lewin", "countries_distinct_count": 2, "cited_by_count": 6, "referenced_works_count": 10}
, {"id": "https://openalex.org/W2325229401", "title": "Mathematics and the Study of Social Relations", "countries_distinct_count": 0, "cited_by_count": 29, "referenced_works_count": 0}
, {"id": "https://openalex.org/W2022625432", "title": "Testing structural-equivalence hypotheses in a network of geographical journals", "countries_distinct_count": 1, "cited_by_count": 27, "referenced_works_count": 19}
, {"id": "https://openalex.org/W2074938484", "title": "On the evolution of group and network structure II: Structures within structure", "countries_distinct_count": 1, "cited_by_count": 26, "referenced_works_count": 13}
, {"id": "https://openalex.org/W1538313430", "title": "Utilizing and Understanding Community Service Provision Networks", "countries_distinct_count": 1, "cited_by_count": 19, "referenced_works_count": 0}
, {"id": "https://openalex.org/W2042929680", "title": "Polyhedral dynamics and conflict mobilization in social networks", "countries_distinct_count": 1, "cited_by_count": 17, "referenced_works_count": 7}
, {"id": "https://openalex.org/W2491255708", "title": "Actor utilities, strategic action and network evolution", "countries_distinct_count": 0, "cited_by_count": 15, "referenced_works_count": 22}
, {"id": "https://openalex.org/W2036423364", "title": "Leveling coalitions as network phenomena", "countries_distinct_count": 1, "cited_by_count": 12, "referenced_works_count": 10}
, {"id": "https://openalex.org/W2588101803", "title": "EVOLUTION OF FRIENDSHIP AND BEST FRIENDSHIP CHOICES", "countries_distinct_count": 0, "cited_by_count": 10, "referenced_works_count": 0}
, {"id": "https://openalex.org/W2183777063", "title": "Absent ties in social networks, their treatments, and blockmodeling outcomes", "countries_distinct_count": 2, "cited_by_count": 9, "referenced_works_count": 35}
, {"id": "https://openalex.org/W2560581294", "title": "Evolution Of Social Networks. Part II. Special Issue Of Journal Of Mathematical Sociology, 25", "countries_distinct_count": 0, "cited_by_count": 9, "referenced_works_count": 0}
, {"id": "https://openalex.org/W106729413", "title": "An effective and efficient subpopulation extraction method in very large social networks", "countries_distinct_count": 2, "cited_by_count": 8, "referenced_works_count": 26}
, {"id": "https://openalex.org/W2022405696", "title": "Identifying Linking-Pin Organizations in Inter-Organizational Networks", "countries_distinct_count": 1, "cited_by_count": 8, "referenced_works_count": 36}
, {"id": "https://openalex.org/W2406626900", "title": "", "countries_distinct_count": 1, "cited_by_count": 8, "referenced_works_count": 9}
, {"id": "https://openalex.org/W2461445468", "title": "Optimizational Approach to Blockmodeling", "countries_distinct_count": 2, "cited_by_count": 8, "referenced_works_count": 0}
, {"id": "https://openalex.org/W2987235078", "title": "Deterministic blockmodelling of signed and two\u2010mode networks: A tutorial with software and psychological examples", "countries_distinct_count": 2, "cited_by_count": 8, "referenced_works_count": 159}
, {"id": "https://openalex.org/W2027443184", "title": "Understanding Information and Knowledge Flows as Network Processes in an Oil Company", "countries_distinct_count": 3, "cited_by_count": 6, "referenced_works_count": 28}
, {"id": "https://openalex.org/W2617245445", "title": "Reflections on Studying Signed Networks", "countries_distinct_count": 2, "cited_by_count": 6, "referenced_works_count": 12}
, {"id": "https://openalex.org/W61699314", "title": "Some Open Problem Sets for Generalized Blockmodeling", "countries_distinct_count": 1, "cited_by_count": 6, "referenced_works_count": 25}
, {"id": "https://openalex.org/W4225114500", "title": "The Koch Brothers and the climate change denial social movement", "countries_distinct_count": 0, "cited_by_count": 5, "referenced_works_count": 0}
, {"id": "https://openalex.org/W2027932987", "title": "On the dynamics of national scientific systems: a reply", "countries_distinct_count": 2, "cited_by_count": 4, "referenced_works_count": 9}
, {"id": "https://openalex.org/W2738945021", "title": "The Case for Adopting Blockmodeling in Human Resource Management Research: Examples in Analyzing Social Networks and HRM Systems", "countries_distinct_count": 0, "cited_by_count": 4, "referenced_works_count": 55}
, {"id": "https://openalex.org/W3134766635", "title": "Public issues, policy proposals, social movements, and the interests of the Koch Brothers network of allies", "countries_distinct_count": 2, "cited_by_count": 4, "referenced_works_count": 49}
, {"id": "https://openalex.org/W3049662938", "title": "Delineating Changes in the Fundamental Structure of Signed Networks", "countries_distinct_count": 2, "cited_by_count": 3, "referenced_works_count": 37}
, {"id": "https://openalex.org/W2897395002", "title": "Deterministic Blockmodeling of Two-Mode Binary Networks Using a Two-Mode <i>KL</i> -Median Heuristic", "countries_distinct_count": 2, "cited_by_count": 2, "referenced_works_count": 56}
, {"id": "https://openalex.org/W2069908251", "title": "An Intuitive Introduction to Blockmodeling with Examples", "countries_distinct_count": 1, "cited_by_count": 13, "referenced_works_count": 21}
, {"id": "https://openalex.org/W2787965219", "title": "Finite Sample Behavior of MLE in Network Autocorrelation Models", "countries_distinct_count": 3, "cited_by_count": 3, "referenced_works_count": 19}
, {"id": "https://openalex.org/W4234948308", "title": "The Problem of Solidarity", "countries_distinct_count": 0, "cited_by_count": 3, "referenced_works_count": 0}
, {"id": "https://openalex.org/W2131273260", "title": "Modeling Social Processes.", "countries_distinct_count": 0, "cited_by_count": 33, "referenced_works_count": 0}
, {"id": "https://openalex.org/W2093383369", "title": "Mathematics and the Study of Social Relations.", "countries_distinct_count": 0, "cited_by_count": 32, "referenced_works_count": 0}
, {"id": "https://openalex.org/W4302603713", "title": "Modeling Social Processes.", "countries_distinct_count": 0, "cited_by_count": 20, "referenced_works_count": 0}
, {"id": "https://openalex.org/W2033749371", "title": "Using multiple network analytic tools for a single social network", "countries_distinct_count": 1, "cited_by_count": 18, "referenced_works_count": 35}
, {"id": "https://openalex.org/W2073358611", "title": "On the ranking of psychological journals", "countries_distinct_count": 1, "cited_by_count": 13, "referenced_works_count": 39}
, {"id": "https://openalex.org/W2046628651", "title": "A Critique of the Multidimensional Approach to Stratification", "countries_distinct_count": 1, "cited_by_count": 11, "referenced_works_count": 0}
, {"id": "https://openalex.org/W2334295779", "title": "Measuring Relative Standing in Small Groups and Bounded Social Networks", "countries_distinct_count": 0, "cited_by_count": 10, "referenced_works_count": 13}
, {"id": "https://openalex.org/W287986997", "title": "On Connecting Network Analysis and Cluster Analysis", "countries_distinct_count": 2, "cited_by_count": 9, "referenced_works_count": 25}
, {"id": "https://openalex.org/W2409179968", "title": "Preface", "countries_distinct_count": 2, "cited_by_count": 8, "referenced_works_count": 0}
, {"id": "https://openalex.org/W2000564095", "title": "Borgatti toppings on Doreian splits: Reflections on regular equivalence", "countries_distinct_count": 1, "cited_by_count": 7, "referenced_works_count": 7}
, {"id": "https://openalex.org/W2154736758", "title": "Discussion on the paper by Handcock, Raftery and Tantrum", "countries_distinct_count": 1, "cited_by_count": 6, "referenced_works_count": 0}
, {"id": "https://openalex.org/W2511469895", "title": "Evolution of social networks. Part II.", "countries_distinct_count": 0, "cited_by_count": 6, "referenced_works_count": 0}
, {"id": "https://openalex.org/W1974423231", "title": "Estimating Differential Equation Models On Time Series", "countries_distinct_count": 1, "cited_by_count": 5, "referenced_works_count": 8}
, {"id": "https://openalex.org/W2069914860", "title": "A note on actor network utilities and network evolution", "countries_distinct_count": 1, "cited_by_count": 5, "referenced_works_count": 6}
, {"id": "https://openalex.org/W2188655339", "title": "Structural Balance and Partitioning Signed Graphs", "countries_distinct_count": 0, "cited_by_count": 4, "referenced_works_count": 11}
, {"id": "https://openalex.org/W2895844042", "title": "STRUCTURAL CONTROL MODELS FOR GROUP PROCESSES", "countries_distinct_count": 1, "cited_by_count": 4, "referenced_works_count": 14}
, {"id": "https://openalex.org/W2327782659", "title": "On the \"Social Law of Effect\" for Task-Oriented Groups", "countries_distinct_count": 0, "cited_by_count": 3, "referenced_works_count": 0}
, {"id": "https://openalex.org/W2400578951", "title": "Networks in Social Psychology: Beginning with Kurt Lewin", "countries_distinct_count": 2, "cited_by_count": 3, "referenced_works_count": 12}
, {"id": "https://openalex.org/W2507149214", "title": "red.).Evolution of social networks", "countries_distinct_count": 0, "cited_by_count": 3, "referenced_works_count": 0}
, {"id": "https://openalex.org/W2953628719", "title": "Signed Networks for the US Supreme Court Overturning its Prior Decisions", "countries_distinct_count": 2, "cited_by_count": 3, "referenced_works_count": 17}
, {"id": "https://openalex.org/W4244993844", "title": "Concluding remarks", "countries_distinct_count": 2, "cited_by_count": 3, "referenced_works_count": 8}
, {"id": "https://openalex.org/W4302587555", "title": "Positional Analysis and Blockmodeling", "countries_distinct_count": 1, "cited_by_count": 3, "referenced_works_count": 17}
, {"id": "https://openalex.org/W2498849726", "title": "Extending Generalized Blockmodeling", "countries_distinct_count": 2, "cited_by_count": 2, "referenced_works_count": 0}
, {"id": "https://openalex.org/W4301306918", "title": "Networks in Social Psychology, Beginning with Kurt Lewin", "countries_distinct_count": 2, "cited_by_count": 2, "referenced_works_count": 12}
, {"id": "https://openalex.org/W3131243455", "title": "The International Reach of the Koch Brothers Network", "countries_distinct_count": 2, "cited_by_count": 1, "referenced_works_count": 16}
, {"id": "https://openalex.org/W4237152786", "title": "THE WEAKNESS OF STRONG TIES: COLLECTIVE ACTION FAILURE IN A HIGHLY COHESIVE GROUP", "countries_distinct_count": 0, "cited_by_count": 1, "referenced_works_count": 0}
, {"id": "https://openalex.org/W4252572651", "title": "Book Reviews: Behavioral Sociology: The Experimental Analysis of Social Process, Balance in Small Groups, Racial Violence in the United States, The Education of Borstal Boys, The Sociology of Religion: A Study of Christendom, IV, Types of Religious Man, Men in Mid-Career: A Study of British Managers and Technical Specialists, The Family and the Handicapped Child: A Study of Cerebral Palsied Children in Their Homes, The Assessment of Social Research: Guidelines for the Use of Social Research in Social Work and Social Science, The Conditions of Social Performance: An Exploratory Theory, Families and Their Relatives: Kinship in a Middle-Class Sector of London, The Population Census: A Social Science Research Council Review, Introduction to Social Work, Theories of Social Psychology, Put Away: A Sociological Study of Institutions for the Mentally Retarded, City Lads in Borstal: A Study Based on 100 Lads Discharged to Addresses in Liverspool, Science, Industry and Society: Studies in the Sociology of Science, Interaction Concept of Personality, Hightown Grammar: The School as a Social System, Causes of Delinquency, towards a Sociology of the Cinema: A Comparative Essay on the Structure and Functioning of a Major Entertainment Industry", "countries_distinct_count": 3, "cited_by_count": 1, "referenced_works_count": 0}
, {"id": "https://openalex.org/W2011349533", "title": "A measure of standing for citation networks within a wider environment", "countries_distinct_count": 1, "cited_by_count": 10, "referenced_works_count": 19}
, {"id": "https://openalex.org/W2406519469", "title": "Book review", "countries_distinct_count": 2, "cited_by_count": 1, "referenced_works_count": 5}
, {"id": "https://openalex.org/W2994903905", "title": "Partitioning Signed Networks", "countries_distinct_count": 3, "cited_by_count": 15, "referenced_works_count": 39}
, {"id": "https://openalex.org/W2502336230", "title": "Introduction", "countries_distinct_count": 1, "cited_by_count": 9, "referenced_works_count": 0}
, {"id": "https://openalex.org/W4236773783", "title": "Introduction", "countries_distinct_count": 2, "cited_by_count": 8, "referenced_works_count": 0}
, {"id": "https://openalex.org/W2051911336", "title": "Analyzing overlaps in food webs", "countries_distinct_count": 1, "cited_by_count": 6, "referenced_works_count": 6}
, {"id": "https://openalex.org/W2510995198", "title": "Evolution of social networks - Introduction", "countries_distinct_count": 0, "cited_by_count": 6, "referenced_works_count": 0}
, {"id": "https://openalex.org/W2995196257", "title": "Bibliometric Analyses of the Network Clustering Literature", "countries_distinct_count": 3, "cited_by_count": 6, "referenced_works_count": 23}
, {"id": "https://openalex.org/W2995396414", "title": "Treating Missing Network Data Before Partitioning", "countries_distinct_count": 3, "cited_by_count": 5, "referenced_works_count": 36}
, {"id": "https://openalex.org/W2021620352", "title": "Models of stratification processes", "countries_distinct_count": 1, "cited_by_count": 4, "referenced_works_count": 23}
, {"id": "https://openalex.org/W2315444210", "title": "Estimates for Differential Equation Models of Social Phenomena", "countries_distinct_count": 0, "cited_by_count": 4, "referenced_works_count": 6}
, {"id": "https://openalex.org/W2050005311", "title": "Multivariate analysis and categorised data", "countries_distinct_count": 0, "cited_by_count": 3, "referenced_works_count": 25}
, {"id": "https://openalex.org/W2161034146", "title": "Una introducci\u00f3n de car\u00e1cter intuitivo a la modelizaci\u00f3n en bloques (Blockmodeling)", "countries_distinct_count": 0, "cited_by_count": 3, "referenced_works_count": 0}
, {"id": "https://openalex.org/W145186482", "title": "Organizational Standing as Corporate Social Capital", "countries_distinct_count": 0, "cited_by_count": 2, "referenced_works_count": 0}
, {"id": "https://openalex.org/W2463651575", "title": "Foundations for Generalized Blockmodeling", "countries_distinct_count": 2, "cited_by_count": 2, "referenced_works_count": 0}
, {"id": "https://openalex.org/W2484836617", "title": "Citation Patterns in Temporal United States Patent Data", "countries_distinct_count": 2, "cited_by_count": 2, "referenced_works_count": 0}
, {"id": "https://openalex.org/W4235477325", "title": "Signed Networks", "countries_distinct_count": 0, "cited_by_count": 2, "referenced_works_count": 0}
, {"id": "https://openalex.org/W1592200103", "title": "Evolution Of Social Networks. Part III: Introduction", "countries_distinct_count": 0, "cited_by_count": 1, "referenced_works_count": 0}
, {"id": "https://openalex.org/W1975103320", "title": "Regoo plots as a regression diagnostic tool", "countries_distinct_count": 1, "cited_by_count": 1, "referenced_works_count": 5}
, {"id": "https://openalex.org/W2074854284", "title": "Corrigendum to \u201cGeneralized blockmodeling of two-mode network data\u201d [Social Networks 26 (2004) 29\u201353]", "countries_distinct_count": 2, "cited_by_count": 1, "referenced_works_count": 0}
, {"id": "https://openalex.org/W2319835252", "title": "Reply to Daft and MacMillan", "countries_distinct_count": 0, "cited_by_count": 1, "referenced_works_count": 0}
, {"id": "https://openalex.org/W2484677419", "title": "Evolution of social networks - Concluding remarks", "countries_distinct_count": 0, "cited_by_count": 1, "referenced_works_count": 0}
, {"id": "https://openalex.org/W2490478333", "title": "Temporal and Spatial Networks", "countries_distinct_count": 2, "cited_by_count": 1, "referenced_works_count": 0}
, {"id": "https://openalex.org/W2791479109", "title": "Partitioning signed networks", "countries_distinct_count": 0, "cited_by_count": 1, "referenced_works_count": 0}
, {"id": "https://openalex.org/W4229767758", "title": "Introduction", "countries_distinct_count": 0, "cited_by_count": 1, "referenced_works_count": 0}
, {"id": "https://openalex.org/W4234286512", "title": "Models of stratification processes", "countries_distinct_count": 0, "cited_by_count": 1, "referenced_works_count": 0}
, {"id": "https://openalex.org/W4243249094", "title": "Introduction", "countries_distinct_count": 3, "cited_by_count": 1, "referenced_works_count": 0}
, {"id": "https://openalex.org/W1018702376", "title": "Semirings and Lattices", "countries_distinct_count": 2, "cited_by_count": 0, "referenced_works_count": 0}
, {"id": "https://openalex.org/W152411804", "title": "Review of Networks: A Very Short Introduction (Very Short Introductions)", "countries_distinct_count": 0, "cited_by_count": 0, "referenced_works_count": 0}
, {"id": "https://openalex.org/W1578974842", "title": "Introduction [to third special issue of the Journal of Mathematical Sociology on Evolution of Social Network]", "countries_distinct_count": 0, "cited_by_count": 0, "referenced_works_count": 0}
, {"id": "https://openalex.org/W1932983376", "title": "Clustering Approaches", "countries_distinct_count": 2, "cited_by_count": 0, "referenced_works_count": 0}
, {"id": "https://openalex.org/W1976162132", "title": "Using a highly portable computer to gather qualitative social network data", "countries_distinct_count": 1, "cited_by_count": 0, "referenced_works_count": 19}
, {"id": "https://openalex.org/W1992782156", "title": "The sociology of research", "countries_distinct_count": 1, "cited_by_count": 0, "referenced_works_count": 0}
, {"id": "https://openalex.org/W2001367215", "title": "Robert Bell &amp; John Coplans. Decisions, Decisions. New York: Norton, 1976, 160 pp., $7.95", "countries_distinct_count": 1, "cited_by_count": 0, "referenced_works_count": 0}
, {"id": "https://openalex.org/W2013766266", "title": "Welfare policy and causal modelling", "countries_distinct_count": 1, "cited_by_count": 0, "referenced_works_count": 8}
, {"id": "https://openalex.org/W2029140398", "title": "Robert K. Leik &amp; Barbara F. Meeker. Mathematical sociology. Engle-wood cliffs, N. J.: Prentice-Hall, 1975, $12.95", "countries_distinct_count": 1, "cited_by_count": 0, "referenced_works_count": 0}
, {"id": "https://openalex.org/W2077060492", "title": "Response Characteristics of the U.S. Scientific and Engineering Labor Force", "countries_distinct_count": 1, "cited_by_count": 0, "referenced_works_count": 10}
, {"id": "https://openalex.org/W21840672", "title": "Optimizational Approach to Conventional Blockmodeling", "countries_distinct_count": 2, "cited_by_count": 0, "referenced_works_count": 0}
, {"id": "https://openalex.org/W2253954811", "title": "Evaluation of a Learning Collaboratives Process and Effectiveness to Reduce Health Care Disparities Among Minority Populations", "countries_distinct_count": 0, "cited_by_count": 0, "referenced_works_count": 0}
, {"id": "https://openalex.org/W228315409", "title": "Formal Approaches to Applied Social Research.", "countries_distinct_count": 0, "cited_by_count": 0, "referenced_works_count": 0}
, {"id": "https://openalex.org/W2296023295", "title": "Understanding a Collaborative Effort to Reduce Racial and Ethnic Disparities in Health Care: Contributions form Social Network Analysis", "countries_distinct_count": 0, "cited_by_count": 0, "referenced_works_count": 0}
, {"id": "https://openalex.org/W2318654923", "title": "The Developmental Logic of Social Systems. By Henry Teune and Zdravko Mlinar. (Beverly Hills, Calif.: Sage Publications, 1978. Pp. 174. $14.00, cloth; $6.95, paper.) - The Social Ecology of Change: From Equilibrium to Development. Edited by Zdravko Mlinar and Henry Teune. (Beverly Hills, Calif.: Sage Publications, 1978. Pp. 296. $14.00.)", "countries_distinct_count": 1, "cited_by_count": 0, "referenced_works_count": 0}
, {"id": "https://openalex.org/W2327726363", "title": "A report by the editor", "countries_distinct_count": 0, "cited_by_count": 0, "referenced_works_count": 0}
, {"id": "https://openalex.org/W2396296264", "title": "Networks: A Very Short Introduction (Very Short Introductions) by Guido Caldarelli and Michele Catanzaro .", "countries_distinct_count": 0, "cited_by_count": 0, "referenced_works_count": 0}
, {"id": "https://openalex.org/W2396776702", "title": "Titles in the series", "countries_distinct_count": 2, "cited_by_count": 0, "referenced_works_count": 0}
, {"id": "https://openalex.org/W2415235604", "title": "Introduction to special issue on evolution of social networks. Part II", "countries_distinct_count": 0, "cited_by_count": 0, "referenced_works_count": 0}
, {"id": "https://openalex.org/W2473101195", "title": "Mathematical Prelude", "countries_distinct_count": 2, "cited_by_count": 0, "referenced_works_count": 0}
, {"id": "https://openalex.org/W2475484939", "title": "Relations and Graphs for Network Analysis", "countries_distinct_count": 2, "cited_by_count": 0, "referenced_works_count": 0}
, {"id": "https://openalex.org/W2479524298", "title": "Methods for Large Networks", "countries_distinct_count": 2, "cited_by_count": 0, "referenced_works_count": 0}
, {"id": "https://openalex.org/W2483749465", "title": "Symmetric\u2013Acyclic Blockmodels", "countries_distinct_count": 2, "cited_by_count": 0, "referenced_works_count": 0}
, {"id": "https://openalex.org/W2489286328", "title": "Mathematics in Sociology: Cinderella's Carriage or Pumpkin?", "countries_distinct_count": 1, "cited_by_count": 0, "referenced_works_count": 21}
, {"id": "https://openalex.org/W2493872177", "title": "Mapping Spatial Diversity in the United States of America", "countries_distinct_count": 2, "cited_by_count": 0, "referenced_works_count": 0}
, {"id": "https://openalex.org/W2496778214", "title": "Networks of Player Movements to the EPL", "countries_distinct_count": 2, "cited_by_count": 0, "referenced_works_count": 0}
, {"id": "https://openalex.org/W2496832405", "title": "Foundations of Methods for Large Networks", "countries_distinct_count": 2, "cited_by_count": 0, "referenced_works_count": 0}
, {"id": "https://openalex.org/W2497008435", "title": "Appendix: Data Documentation", "countries_distinct_count": 2, "cited_by_count": 0, "referenced_works_count": 0}
, {"id": "https://openalex.org/W2500306725", "title": "On Studying Large Networks", "countries_distinct_count": 2, "cited_by_count": 0, "referenced_works_count": 0}
, {"id": "https://openalex.org/W2529589167", "title": "ON THE SAMPLING DISTRIBUTIONS OF THE ML ESTIMATORS IN NETWORK EFFECT MODELS", "countries_distinct_count": 2, "cited_by_count": 0, "referenced_works_count": 11}
, {"id": "https://openalex.org/W2573143169", "title": "Clashing Paradigms and Mathematics in the Social Sciences", "countries_distinct_count": 1, "cited_by_count": 0, "referenced_works_count": 0}
, {"id": "https://openalex.org/W2582492955", "title": "Assessing the effect of student networks on academic performance", "countries_distinct_count": 0, "cited_by_count": 0, "referenced_works_count": 0}
, {"id": "https://openalex.org/W2604210617", "title": "Resampling regression models in the presence of network effects", "countries_distinct_count": 0, "cited_by_count": 0, "referenced_works_count": 0}
, {"id": "https://openalex.org/W2607222141", "title": "A model for the analysis of adoption behavior through network effects", "countries_distinct_count": 1, "cited_by_count": 0, "referenced_works_count": 0}
, {"id": "https://openalex.org/W2804599476", "title": "Including Network Effect in Structural Equation Models: Student Communities and Performance", "countries_distinct_count": 0, "cited_by_count": 0, "referenced_works_count": 0}
, {"id": "https://openalex.org/W2806683686", "title": "On the sampling distribution of the ML estimators in Network Autocorrelation Models", "countries_distinct_count": 0, "cited_by_count": 0, "referenced_works_count": 0}
, {"id": "https://openalex.org/W2952957530", "title": "Contrasting Multiple Social Network Autocorrelations for Binary Outcomes, With Applications To Technology Adoption", "countries_distinct_count": 0, "cited_by_count": 0, "referenced_works_count": 22}
, {"id": "https://openalex.org/W2996211974", "title": "Conclusions and Directions for Future Work", "countries_distinct_count": 3, "cited_by_count": 0, "referenced_works_count": 15}
, {"id": "https://openalex.org/W3215871122", "title": "Book Review: <i>The Oxford Handbook of Social Networks</i>", "countries_distinct_count": 2, "cited_by_count": 0, "referenced_works_count": 0}
, {"id": "https://openalex.org/W4205330654", "title": "Front Matter", "countries_distinct_count": 3, "cited_by_count": 0, "referenced_works_count": 0}
, {"id": "https://openalex.org/W4206540507", "title": "Preface to the special issue", "countries_distinct_count": 3, "cited_by_count": 0, "referenced_works_count": 6}
, {"id": "https://openalex.org/W4211090342", "title": "References", "countries_distinct_count": 2, "cited_by_count": 0, "referenced_works_count": 161}
, {"id": "https://openalex.org/W4212962993", "title": "Book Reviews: The Sociology of Max Weber, Society and Democracy in Germany, Latent Structure Analysis, The Sociology of Marx, Delinquents and Non-delinquents in Perspective, Moral Education, Explanation in Social Science: A System Paradigm, The Coloured Worker in British Industry, The Cloistered Elite, Essays on Research in the Sociology of Religion, Family and Kinship in Modern Britain, Readings in Mathematical Social Science, The Sociology of Education, The Protestant Ethic and Modernization, British Parliamentary Election Statistics 1918\u20131968, The British Voter, Experiment in Industrial Democracy: A Study of the John Lewis Partnership, Artistic Expression\u2014A Sociological Analysis, The Logic of Collective Action: Public Goods and the Theory of Groups, Sociology and the Stereotype of the Criminal, Social Class and Delinquency", "countries_distinct_count": 4, "cited_by_count": 0, "referenced_works_count": 0}
, {"id": "https://openalex.org/W4232159006", "title": "Person Index", "countries_distinct_count": 2, "cited_by_count": 0, "referenced_works_count": 0}
, {"id": "https://openalex.org/W4234403230", "title": "Subject Index", "countries_distinct_count": 2, "cited_by_count": 0, "referenced_works_count": 0}
, {"id": "https://openalex.org/W4234739210", "title": "Person Index", "countries_distinct_count": 3, "cited_by_count": 0, "referenced_works_count": 1}
, {"id": "https://openalex.org/W4234973756", "title": "Scientific Citation and Other Bibliographic Networks", "countries_distinct_count": 2, "cited_by_count": 0, "referenced_works_count": 7}
, {"id": "https://openalex.org/W4234993934", "title": "Bibliography", "countries_distinct_count": 2, "cited_by_count": 0, "referenced_works_count": 0}
, {"id": "https://openalex.org/W4237035053", "title": "Abstracts", "countries_distinct_count": 0, "cited_by_count": 0, "referenced_works_count": 0}
, {"id": "https://openalex.org/W4237535301", "title": "Book review", "countries_distinct_count": 1, "cited_by_count": 0, "referenced_works_count": 0}
, {"id": "https://openalex.org/W4244285180", "title": "Book Reviews: Campus Power Struggle, Theory Construction: From Verbal to Mathematical Formulations, Personality and Religion: The R\u00f4le of Religion in Personality Development, Social Relations in a Secondary School, Society and Economic Growth: A Behavioural Perspective of Social Change, Sociology, History and Education: A Reader, Social Research and Social Policy, The Emergence of Society, The Philosophy of Social Science, Television and Delinquency, Foster Care: Theory and Practice, The Sociological Study of Religion, Basic Readings in the Sociology of Education, Social System and Time and Space, II Cluster Analysis", "countries_distinct_count": 3, "cited_by_count": 0, "referenced_works_count": 0}
, {"id": "https://openalex.org/W4250818470", "title": "Topic Index", "countries_distinct_count": 3, "cited_by_count": 0, "referenced_works_count": 0}
, {"id": "https://openalex.org/W4251058520", "title": "Book Reviews: Politics of Social Research: An Inquiry into the Ethics and Responsibilities of Social Scientists, Organisational Behavior, Construction of Preference Spaces: An Investigation into the Applicability of Multidimensional Scaling Models, The Theory of Social Change: Four Views Considered, Middle Age and Aging, The Business Enterprise in Modern Industrial Society, Curing for Children in Trouble, The Family, The Theory and Practice of Vocational Guidance: A Selection of Readings, The Concept of Community, The Desegregation of the Mentally Ill, Max Weber on Charisma and Institution Building, towards a Sociology of Mass Communications, The Logic of Social Inquiry, Computer Methods in the Analysis of Large-Scale Social Systems, Social Networks in Urban Situations, Ownership, Control, and Ideology, Small Town in Mass Society: Class, Power and Religion in a Rural Community, Modernizing Peasant Societies: A Comparative Study in Asia and Africa, Sport, Culture, and Society: A Reader on the Sociology of Sport, Adolescent Girls in Approved Schools, Studies in British Society, Social Research, Values and Involvement in a Grammar School", "countries_distinct_count": 2, "cited_by_count": 0, "referenced_works_count": 0}
, {"id": "https://openalex.org/W4256123129", "title": "Book reviews", "countries_distinct_count": 1, "cited_by_count": 0, "referenced_works_count": 0}
, {"id": "https://openalex.org/W42799514", "title": "Balance Theory and Blockmodeling Signed Networks", "countries_distinct_count": 2, "cited_by_count": 0, "referenced_works_count": 0}
, {"id": "https://openalex.org/W4389501302", "title": "Balance Correlations, Agentic Zeros, and Networks: The Structure of 192 Years of War and Peace", "countries_distinct_count": 0, "cited_by_count": 0, "referenced_works_count": 0}
, {"id": "https://openalex.org/W4392912593", "title": "Blockmodeling, Positions and Roles", "countries_distinct_count": 0, "cited_by_count": 0, "referenced_works_count": 0}
, {"id": "https://openalex.org/W4399049829", "title": "Network Clustering", "countries_distinct_count": 2, "cited_by_count": 0, "referenced_works_count": 46}
, {"id": "https://openalex.org/W4405655847", "title": "Balance correlations, agentic zeros, and networks: The structure of 192 years of war and peace", "countries_distinct_count": 4, "cited_by_count": 0, "referenced_works_count": 43}
, {"id": "https://openalex.org/W4408324191", "title": "Identifying Fragments in Networks for Structural Balance and Tracking the Levels of Balance Over Time", "countries_distinct_count": 1, "cited_by_count": 0, "referenced_works_count": 20}
, {"id": "https://openalex.org/W759846306", "title": "Auto-probit Model for Multiple Regimes of Network Effects", "countries_distinct_count": 0, "cited_by_count": 0, "referenced_works_count": 17}
, {"id": "https://openalex.org/W934096901", "title": "Blockmodeling Two-Mode Network Data", "countries_distinct_count": 2, "cited_by_count": 0, "referenced_works_count": 0}
], "group_by": []}
